fastapi_swagger2/__init__.py
fastapi_swagger2/models.py
fastapi_swagger2/utils.py
fastapi_swagger2-0.3.2.dist-info/METADATA
fastapi_swagger2-0.3.2.dist-info/WHEEL
fastapi_swagger2-0.3.2.dist-info/licenses/LICENSE
fastapi_swagger2-0.3.2.dist-info/RECORD
