Metadata-Version: 2.4
Name: fastapi_swagger2
Version: 0.3.2
Summary: Swagger2 support for FastAPI framework
Project-URL: Homepage, https://github.com/virajkanwade/fastapi_swagger2
Project-URL: Documentation, https://github.com/virajkanwade/fastapi_swagger2
Author-email: Viraj Kanwade <virajk.oib@gmail.com>
License: MIT License
License-File: LICENSE
Classifier: Environment :: Web Environment
Classifier: Framework :: AsyncIO
Classifier: Framework :: FastAPI
Classifier: Framework :: Pydantic
Classifier: Framework :: Pydantic :: 1
Classifier: Intended Audience :: Developers
Classifier: Intended Audience :: Information Technology
Classifier: Intended Audience :: System Administrators
Classifier: License :: OSI Approved :: MIT License
Classifier: Operating System :: OS Independent
Classifier: Programming Language :: Python
Classifier: Programming Language :: Python :: 3
Classifier: Programming Language :: Python :: 3 :: Only
Classifier: Programming Language :: Python :: 3.9
Classifier: Programming Language :: Python :: 3.10
Classifier: Programming Language :: Python :: 3.11
Classifier: Programming Language :: Python :: 3.12
Classifier: Programming Language :: Python :: 3.13
Classifier: Topic :: Internet
Classifier: Topic :: Internet :: WWW/HTTP
Classifier: Topic :: Internet :: WWW/HTTP :: HTTP Servers
Classifier: Topic :: Software Development
Classifier: Topic :: Software Development :: Libraries
Classifier: Topic :: Software Development :: Libraries :: Python Modules
Classifier: Typing :: Typed
Requires-Python: >=3.9
Requires-Dist: fastapi>=0.128.0
Provides-Extra: all
Requires-Dist: httpx>=0.28.1; extra == 'all'
Provides-Extra: dev
Requires-Dist: ruff==0.14.10; extra == 'dev'
Provides-Extra: test
Requires-Dist: black==25.12.0; extra == 'test'
Requires-Dist: coverage[toml]<8.0,>=7.13.1; extra == 'test'
Requires-Dist: httpx>=0.28.1; extra == 'test'
Requires-Dist: isort>=7.0.0; extra == 'test'
Requires-Dist: mypy==1.19.1; extra == 'test'
Requires-Dist: pytest<10.0.0,>=9.0.2; extra == 'test'
Requires-Dist: ruff==0.14.10; extra == 'test'
